PygameAnimationLib/__init__.py
PygameUILib/__init__.py
PygameUILib-0.0.2.dist-info/LICENSE
PygameUILib-0.0.2.dist-info/METADATA
PygameUILib-0.0.2.dist-info/WHEEL
PygameUILib-0.0.2.dist-info/top_level.txt
PygameUILib-0.0.2.dist-info/RECORD
