Metadata-Version: 2.1
Name: PygameUILib
Version: 0.0.2
Summary: An easy-to-use pygame User Interface Library
Home-page: https://github.com/Hugo4IT/PygameUILib
Author: Hugo van de Kuilen from Hugo4IT.com
Author-email: hugo.vandekuilen1234567890@gmail.com
License: UNKNOWN
Platform: UNKNOWN
Classifier: Programming Language :: Python :: 3
Classifier: License :: OSI Approved :: MIT License
Classifier: Operating System :: OS Independent
